README.rst
setup.py
gbboxcli/__init__.py
gbboxcli/api.py
gbboxcli/cli.py
gbboxcli.egg-info/PKG-INFO
gbboxcli.egg-info/SOURCES.txt
gbboxcli.egg-info/dependency_links.txt
gbboxcli.egg-info/entry_points.txt
gbboxcli.egg-info/requires.txt
gbboxcli.egg-info/top_level.txt
gbboxcli/tests/__init__.py
gbboxcli/tests/test_api.py